addicted/__init__.py
addicted3-3.0.1.dist-info/LICENSE.txt
addicted3-3.0.1.dist-info/METADATA
addicted3-3.0.1.dist-info/WHEEL
addicted3-3.0.1.dist-info/eager_resources.txt
addicted3-3.0.1.dist-info/top_level.txt
addicted3-3.0.1.dist-info/RECORD
