Metadata-Version: 2.1
Name: addicted3
Version: 3.0.1
Summary: Enhanced dict for python 3
Home-page: https://github.com/elapouya/addicted3
Author: Eric Lapouyade
Author-email: elapouya@gmail.com
License: LGPL 2.1
Keywords: attribute AttrDict addict addicted textops naghelp
Platform: UNKNOWN
Classifier: Intended Audience :: Developers
Classifier: Development Status :: 4 - Beta
Classifier: Programming Language :: Python :: 3
License-File: LICENSE.txt
